{
  "main": {
    "id": "ab96fbce3dac8969",
    "type": "split",
    "children": [
      {
        "id": "786ebcc31bfff29a",
        "type": "tabs",
        "children": [
          {
            "id": "0a9fe4fa63863c3e",
            "type": "leaf",
            "state": {
              "type": "markdown",
              "state": {
                "file": "DATABACE/Session/Database Session.md",
                "mode": "source",
                "source": false
              }
            }
          },
          {
            "id": "bf7488212a1498c8",
            "type": "leaf",
            "state": {
              "type": "markdown",
              "state": {
                "file": "DATABACE/Object/Object.md",
                "mode": "source",
                "source": false
              }
            }
          },
          {
            "id": "17860f05d57aa626",
            "type": "leaf",
            "state": {
              "type": "markdown",
              "state": {
                "file": "DATABACE/SQL/sql hint direct load insert.md",
                "mode": "source",
                "source": false
              }
            }
          },
          {
            "id": "fd3c452eec1f521f",
            "type": "leaf",
            "state": {
              "type": "markdown",
              "state": {
                "file": "DATABACE/lock/exclusive lock.md",
                "mode": "source",
                "source": false
              }
            }
          },
          {
            "id": "bbf22f1b71de3bfd",
            "type": "leaf",
            "state": {
              "type": "release-notes",
              "state": {
                "currentVersion": "1.5.3"
              }
            }
          },
          {
            "id": "ee3f05d933bc3efc",
            "type": "leaf",
            "state": {
              "type": "release-notes",
              "state": {
                "currentVersion": "1.5.8"
              }
            }
          }
        ],
        "currentTab": 5
      }
    ],
    "direction": "vertical"
  },
  "left": {
    "id": "63bc25cd7186733d",
    "type": "split",
    "children": [
      {
        "id": "6e0c5c11c3025ec0",
        "type": "tabs",
        "children": [
          {
            "id": "d82a90a3765e3847",
            "type": "leaf",
            "state": {
              "type": "file-explorer",
              "state": {
                "sortOrder": "alphabetical"
              }
            }
          },
          {
            "id": "4aa74f484a4d0dad",
            "type": "leaf",
            "state": {
              "type": "search",
              "state": {
                "query": "",
                "matchingCase": false,
                "explainSearch": false,
                "collapseAll": false,
                "extraContext": false,
                "sortOrder": "alphabetical"
              }
            }
          },
          {
            "id": "4822b16f070add57",
            "type": "leaf",
            "state": {
              "type": "bookmarks",
              "state": {}
            }
          }
        ]
      }
    ],
    "direction": "horizontal",
    "width": 300
  },
  "right": {
    "id": "f34860017f89a8c4",
    "type": "split",
    "children": [
      {
        "id": "93cba305b22c4b0c",
        "type": "tabs",
        "children": [
          {
            "id": "3c74e516a0ccf1f9",
            "type": "leaf",
            "state": {
              "type": "backlink",
              "state": {
                "file": "DATABACE/lock/exclusive lock.md",
                "collapseAll": false,
                "extraContext": false,
                "sortOrder": "alphabetical",
                "showSearch": false,
                "searchQuery": "",
                "backlinkCollapsed": false,
                "unlinkedCollapsed": true
              }
            }
          },
          {
            "id": "90303b970e8194b4",
            "type": "leaf",
            "state": {
              "type": "outgoing-link",
              "state": {
                "file": "DATABACE/lock/exclusive lock.md",
                "linksCollapsed": false,
                "unlinkedCollapsed": true
              }
            }
          },
          {
            "id": "41a298a892f5da54",
            "type": "leaf",
            "state": {
              "type": "tag",
              "state": {
                "sortOrder": "frequency",
                "useHierarchy": true
              }
            }
          },
          {
            "id": "36d029a7a8d16c9a",
            "type": "leaf",
            "state": {
              "type": "outline",
              "state": {
                "file": "DATABACE/lock/exclusive lock.md"
              }
            }
          }
        ]
      }
    ],
    "direction": "horizontal",
    "width": 300,
    "collapsed": true
  },
  "left-ribbon": {
    "hiddenItems": {
      "switcher:퀵 스위처 열기": false,
      "graph:그래프 뷰 열기": false,
      "canvas:새 캔버스 만들기": false,
      "daily-notes:오늘의 데일리 노트 열기": false,
      "templates:템플릿 삽입": false,
      "command-palette:명령어 팔레트 열기": false
    }
  },
  "active": "ee3f05d933bc3efc",
  "lastOpenFiles": [
    "DATABACE/SQL/insert 와 delete 의 차이.md",
    "DATABACE/SQL/sql hint direct load insert.md",
    "DATABACE/SQL/insert 를 빠르게 하는법.md",
    "DATABACE/Object/table space 조회.md",
    "DATABACE/lock/share lock.md",
    "DATABACE/Object/redo log 확인.md",
    "DATABACE/Object/ROWNUM.md",
    "conflict-files-obsidian-git.md",
    "DATABACE/Object/Object.md",
    "DATABACE/Object/테이블 스페이스 확인.md",
    "DATABACE/Object/온라인 인덱스.md",
    "DATABACE/Object/Undo Segment.md",
    "DATABACE/Session/Database Session.md",
    "DATABACE/Session/Worker Process.md",
    "Tibero/TSC.md",
    "패치 할때 crf 파일 백업 꼭 해야한다.md",
    "cmrctl del service --name '이름' segsegv 상황.md",
    "tac.md",
    "OS/유닉스 와 리눅스 차이.md",
    "DATABACE/lock/Lock.md",
    "DATABACE/lock/exclusive lock.md",
    "무제 폴더",
    "Tibero",
    "DATABACE/Session",
    "DATABACE/Object",
    "Pasted image 20230913092719.png.md",
    "Pasted image 20230925135000.png.md",
    "OS/Pasted image 20230925135000.png",
    "OS/Pasted image 20230925134900.png",
    "DATABACE/SQL/insert 를 빠르게 하는법",
    "DATABACE/OBJECT/undoSegment.md",
    "DATABACE/OBJECT/ROWNUM.md",
    "DATABACE/OBJECT/온라인 인덱스.md",
    "DATABACE/lock",
    "DATABACE/OBJECT",
    "DATABACE/SQL",
    "DATABACE",
    "tibero"
  ]
}